eventstreaming/__init__.py
eventstreaming/io_event.py
eventstreaming/screen_recorder.py
eventstreaming/stream.py
eventstreaming/websocket/__init__.py
eventstreaming/websocket/index.html
eventstreaming/websocket/index.js
eventstreaming/websocket/io_event.py
eventstreaming/websocket/screen_recorder.py
eventstreaming/websocket/server.py
eventstreaming/websocket/stream.py
eventstreaming/websocket/video.py
eventstreaming/websocket/web_server.py
eventstreaming/websocket/ws_server.py
eventstreaming-0.0.3.dist-info/METADATA
eventstreaming-0.0.3.dist-info/WHEEL
eventstreaming-0.0.3.dist-info/entry_points.txt
eventstreaming-0.0.3.dist-info/licenses/LICENSE
eventstreaming-0.0.3.dist-info/RECORD
